{
  "compressionlevel": -1,
  "height": 10,
  "infinite": false,
  "layers": [
    {
      "type": "imagelayer",
      "name": "icon_sleep",
      "visible": false,
      "opacity": 1,
      "image": "../assets/icons/sleep.png",
      "x": 160,
      "y": 224
    },
    {
      "type": "imagelayer",
      "name": "icon_meal",
      "visible": false,
      "opacity": 1,
      "image": "../assets/icons/meal.png",
      "x": 256,
      "y": 128
    },
    {
      "type": "imagelayer",
      "name": "icon_toilet",
      "visible": false,
      "opacity": 1,
      "image": "../assets/icons/toilet.png",
      "x": 96,
      "y": 288
    },
    {
      "type": "imagelayer",
      "name": "icon_out",
      "visible": false,
      "opacity": 1,
      "image": "../assets/icons/out.png",
      "x": 32,
      "y": 32
    }
  ],
  "nextlayerid": 5,
  "nextobjectid": 1,
  "orientation": "orthogonal",
  "properties": [
    {
      "name": "script",
      "type": "string",
      "value": "plugins/aruba/plugin.js"
    }
  ],
  "renderorder": "right-down",
  "tiledversion": "1.10.2",
  "tileheight": 32,
  "tilesets": [],
  "tilewidth": 32,
  "type": "map",
  "version": "1.10",
  "width": 10
}